webtransport/__init__.py
webtransport/__main__.py
webtransport/config.py
webtransport/server.py
webtransport/handlers/__init__.py
webtransport/handlers/base.py
webtransport/handlers/counter.py
webtransport/handlers/echo.py
webtransport/protocols/__init__.py
webtransport/protocols/http3.py
webtransport/utils/cert.py
webtransport/utils/config.py
webtransport/utils/logging.py
webtransport-0.0.1.dev0.dist-info/METADATA
webtransport-0.0.1.dev0.dist-info/WHEEL
webtransport-0.0.1.dev0.dist-info/entry_points.txt
webtransport-0.0.1.dev0.dist-info/RECORD
